{
  "slip-and-fall": "slip-and-fall",
  "slip-fall-wet-weather": "slip-and-fall",
  "escalator-elevator": "premises_liability_general",
  "food-court-restaurant": "premises_liability_general",
  "retail-shop-injuries": "premises_liability_general",
  "jet-bridge-boarding": "premises_liability_general",
  "boarding-stairs-ramps": "premises_liability_general",
  "disabled-passenger-assistance": "premises_liability_general",
  "baggage-claim": "baggage-claim",
  "luggage-cart-conveyor": "baggage-claim",
  "lost-delayed-luggage": "baggage-claim",
  "vehicle-accidents": "vehicle-accidents",
  "shuttle-bus-ground-transportation": "vehicle-accidents",
  "parking-lot-curbside": "premises_liability_general",
  "rental-car-accidents": "vehicle-accidents",
  "assault-security-failure": "assault-security-failure",
  "security-checkpoint": "security-checkpoint",
  "worker-accidents": "worker-accidents",
  "tarmac-airside": "worker-accidents",
  "construction-zone": "worker-accidents",
  "toxic-exposure": "toxic-exposure",
  "medical-emergency-negligence": "medical-emergency-negligence",
  "international-travel-claims": "baggage-claim",
  "airline-delay-cancellation-injury": "premises_liability_general",
  "child-unaccompanied-minor": "premises_liability_general"
}